odoo/addons/sale_stock_expiry_date_on_qty_at_date_widget/README.rst
odoo/addons/sale_stock_expiry_date_on_qty_at_date_widget/__init__.py
odoo/addons/sale_stock_expiry_date_on_qty_at_date_widget/__manifest__.py
odoo/addons/sale_stock_expiry_date_on_qty_at_date_widget/i18n/es.po
odoo/addons/sale_stock_expiry_date_on_qty_at_date_widget/i18n/sale_stock_expiry_date_on_qty_at_date_widget.pot
odoo/addons/sale_stock_expiry_date_on_qty_at_date_widget/models/__init__.py
odoo/addons/sale_stock_expiry_date_on_qty_at_date_widget/models/sale_order_line.py
odoo/addons/sale_stock_expiry_date_on_qty_at_date_widget/readme/CONFIGURE.md
odoo/addons/sale_stock_expiry_date_on_qty_at_date_widget/readme/CONTEXT.md
odoo/addons/sale_stock_expiry_date_on_qty_at_date_widget/readme/CONTRIBUTORS.md
odoo/addons/sale_stock_expiry_date_on_qty_at_date_widget/readme/DESCRIPTION.md
odoo/addons/sale_stock_expiry_date_on_qty_at_date_widget/readme/INSTALL.md
odoo/addons/sale_stock_expiry_date_on_qty_at_date_widget/readme/USAGE.md
odoo/addons/sale_stock_expiry_date_on_qty_at_date_widget/static/description/exp_date_widget.png
odoo/addons/sale_stock_expiry_date_on_qty_at_date_widget/static/description/icon.png
odoo/addons/sale_stock_expiry_date_on_qty_at_date_widget/static/description/index.html
odoo/addons/sale_stock_expiry_date_on_qty_at_date_widget/static/src/widgets/qty_at_date_widget.esm.js
odoo/addons/sale_stock_expiry_date_on_qty_at_date_widget/static/src/widgets/qty_at_date_widget.xml
odoo/addons/sale_stock_expiry_date_on_qty_at_date_widget/tests/__init__.py
odoo/addons/sale_stock_expiry_date_on_qty_at_date_widget/tests/test_predicted_expiry_date.py
odoo/addons/sale_stock_expiry_date_on_qty_at_date_widget/views/sale_order_line_view.xml
odoo/addons/sale_stock_expiry_date_on_qty_at_date_widget/views/stock_quant_view.xml
odoo_addon_sale_stock_expiry_date_on_qty_at_date_widget-16.0.1.0.1.dist-info/METADATA
odoo_addon_sale_stock_expiry_date_on_qty_at_date_widget-16.0.1.0.1.dist-info/WHEEL
odoo_addon_sale_stock_expiry_date_on_qty_at_date_widget-16.0.1.0.1.dist-info/top_level.txt
odoo_addon_sale_stock_expiry_date_on_qty_at_date_widget-16.0.1.0.1.dist-info/RECORD
